setup.py
invoicing/__init__.py
invoicing/invoice.py
smiles_invoicing.egg-info/PKG-INFO
smiles_invoicing.egg-info/SOURCES.txt
smiles_invoicing.egg-info/dependency_links.txt
smiles_invoicing.egg-info/requires.txt
smiles_invoicing.egg-info/top_level.txt